gkquiztool/IQuiz.py
gkquiztool/__init__.py
gkquiztool-1.0.dist-info/LICENSE
gkquiztool-1.0.dist-info/METADATA
gkquiztool-1.0.dist-info/WHEEL
gkquiztool-1.0.dist-info/top_level.txt
gkquiztool-1.0.dist-info/RECORD
